fastsso/__init__.py
fastsso/django/__init__.py
fastsso/django/core/__init__.py
fastsso/django/middleware/__init__.py
fastsso/django/middleware/kc_middleware.py
fastsso/django/utils/permissions.py
fastsso/fastapi/__init__.py
fastsso/fastapi/core/__init__.py
fastsso/fastapi/core/currentuser.py
fastsso/fastapi/core/exceptions.py
fastsso/fastapi/decorators.py
fastsso/fastapi/logging.py
fastsso/fastapi/middleware/__init__.py
fastsso/fastapi/middleware/keycloak_middleware.py
fastsso/fastapi/utils/__init__.py
fastsso/fastapi/utils/keycloak_validator.py
fastsso/fastapi/utils/unprotected_endpoints.py
fastsso/fastapi/utils/user.py
fastsso/streamlit/__init__.py
fastsso-1.0.1a0.dist-info/LICENSE
fastsso-1.0.1a0.dist-info/METADATA
fastsso-1.0.1a0.dist-info/WHEEL
fastsso-1.0.1a0.dist-info/RECORD
