Metadata-Version: 2.1
Name: fastsso
Version: 1.0.1a0
Summary: 
Author: Alexandre Meline
Requires-Python: >=3.10,<4.0
Classifier: Programming Language :: Python :: 3
Classifier: Programming Language :: Python :: 3.10
Classifier: Programming Language :: Python :: 3.11
Classifier: Programming Language :: Python :: 3.12
Requires-Dist: fastapi[all] (>=0.104.1,<0.105.0)
Requires-Dist: pydantic (>=2.4.2,<3.0.0)
Requires-Dist: python-keycloak (>=3.3.0,<4.0.0)
Requires-Dist: uvicorn (>=0.24.0.post1,<0.25.0)
